[
    {
        "name": "id",
        "dbType": "increments",
        "htmlType": "",
        "validations": "",
        "searchable": false,
        "fillable": false,
        "primary": true,
        "inForm": false,
        "inIndex": false,
        "inView": false
    },
    {
        "name": "code",
        "dbType": "text",
        "htmlType": "text",
        "validations": "required",
        "searchable": true,
        "fillable": true,
        "primary": true,
        "inForm": true,
        "inIndex": true,
        "inView": true
    },
    {
        "name": "description",
        "dbType": "text",
        "htmlType": "text",
        "validations": "",
        "searchable": true,
        "fillable": true,
        "primary": false,
        "inForm": true,
        "inIndex": true,
        "inView": true
    },
    {
        "name": "value",
        "dbType": "text",
        "htmlType": "text",
        "validations": "required",
        "searchable": true,
        "fillable": true,
        "primary": false,
        "inForm": true,
        "inIndex": true,
        "inView": true
    },
    {
        "name": "sequence",
        "dbType": "integer",
        "htmlType": "number",
        "validations": "required",
        "searchable": true,
        "fillable": true,
        "primary": false,
        "inForm": true,
        "inIndex": true,
        "inView": true
    },
    {
        "name": "STR_UDF1",
        "dbType": "text",
        "htmlType": "text",
        "validations": "",
        "searchable": true,
        "fillable": true,
        "primary": false,
        "inForm": true,
        "inIndex": true,
        "inView": true
    },
    {
        "name": "STR_UDF2",
        "dbType": "text",
        "htmlType": "text",
        "validations": "",
        "searchable": true,
        "fillable": true,
        "primary": false,
        "inForm": true,
        "inIndex": true,
        "inView": true
    },
    {
        "name": "STR_UDF3",
        "dbType": "text",
        "htmlType": "text",
        "validations": "",
        "searchable": true,
        "fillable": true,
        "primary": false,
        "inForm": true,
        "inIndex": true,
        "inView": true
    },
    {
        "name": "INT_UDF1",
        "dbType": "integer",
        "htmlType": "number",
        "validations": "",
        "searchable": true,
        "fillable": true,
        "primary": false,
        "inForm": true,
        "inIndex": true,
        "inView": true
    },
    {
        "name": "INT_UDF2",
        "dbType": "integer",
        "htmlType": "number",
        "validations": "",
        "searchable": true,
        "fillable": true,
        "primary": false,
        "inForm": true,
        "inIndex": true,
        "inView": true
    },
    {
        "name": "INT_UDF3",
        "dbType": "integer",
        "htmlType": "number",
        "validations": "",
        "searchable": true,
        "fillable": true,
        "primary": false,
        "inForm": true,
        "inIndex": true,
        "inView": true
    },
    {
        "name": "created_at",
        "dbType": "timestamp",
        "htmlType": "",
        "validations": "",
        "searchable": false,
        "fillable": false,
        "primary": false,
        "inForm": false,
        "inIndex": false,
        "inView": true
    },
    {
        "name": "updated_at",
        "dbType": "timestamp",
        "htmlType": "",
        "validations": "",
        "searchable": false,
        "fillable": false,
        "primary": false,
        "inForm": false,
        "inIndex": false,
        "inView": true
    }
]